supermemory_openai/__init__.py
supermemory_openai/exceptions.py
supermemory_openai/middleware.py
supermemory_openai/tools.py
supermemory_openai/utils.py
supermemory_openai_sdk-1.0.2.dist-info/METADATA
supermemory_openai_sdk-1.0.2.dist-info/WHEEL
supermemory_openai_sdk-1.0.2.dist-info/licenses/LICENSE
supermemory_openai_sdk-1.0.2.dist-info/RECORD
