Metadata-Version: 2.4
Name: supermemory-openai-sdk
Version: 1.0.2
Summary: Memory tools for OpenAI function calling with supermemory
Project-URL: Homepage, https://supermemory.ai
Project-URL: Repository, https://github.com/supermemoryai/supermemory
Project-URL: Documentation, https://supermemory.ai/docs
License-Expression: MIT
License-File: LICENSE
Keywords: ai,memory,openai,supermemory
Classifier: Development Status :: 3 - Alpha
Classifier: Intended Audience :: Developers
Classifier: License :: OSI Approved :: MIT License
Classifier: Programming Language :: Python :: 3
Classifier: Programming Language :: Python :: 3.8
Classifier: Programming Language :: Python :: 3.9
Classifier: Programming Language :: Python :: 3.10
Classifier: Programming Language :: Python :: 3.11
Classifier: Programming Language :: Python :: 3.12
Classifier: Topic :: Scientific/Engineering :: Artificial Intelligence
Classifier: Topic :: Software Development :: Libraries :: Python Modules
Requires-Python: >=3.8.1
Requires-Dist: openai>=1.102.0
Requires-Dist: requests>=2.25.0
Requires-Dist: supermemory>=3.1.0
Requires-Dist: typing-extensions>=4.0.0
Provides-Extra: async
Requires-Dist: aiohttp>=3.8.0; extra == 'async'
